{
    "0": {
        "roomId": 0,
        "roomName": "Dormitorio",
        "roomDescription": "Dormitorio non molto grande dove dormi con i tuoi colleghi, vicino al suo letto c'è l'agente \u001B[34ma13\u001B[0m, a nord trovi la sala \u001B[32mmeeting\u001B[0m.",
        "lookDescription": "Sei nel dormitorio, vicino a te c'è un tuo collega, l'agente \u001B[34ma13\u001B[0m sullo scaffale trovi una serie di \u001B[33mbombole\u001B[0m con dentro l'ossigeno, a nord trovi la \u001B[32msala meeting\u001B[0m.",
        "floorNumber": 0,
        "locked": false,
        "south": null,
        "north": 1,
        "west": null,
        "est": null,
        "items": [
            4
        ],
        "characters": [
            0
        ],
        "oxygen": true,
        "passwordRequired": false
    },
    "1": {
        "roomId": 1,
        "roomName": "Sala meeting",
        "roomDescription": "Sala meeting, dove si tengono le riunioni con i colleghi, al centro della stanza c'è il \u001B[34mcomandante\u001B[0m, ad est trovi il \u001B[32mlaboratorio\u001B[0m, a sud il \u001B[32mdormitorio\u001B[0m, mentre a ovest trovi le scale per raggiungere la \u001B[32mmensa\u001B[0m",
        "lookDescription": "Sei nella sala meeting, al centro della stanza c'è il \u001B[34mcomandante\u001B[0m seduto sulla poltrona ergonomica, \nsul tavolo trovi una \u001B[33mpistola\u001B[0m, a sud trovi il \u001B[32mdormitorio\u001B[0m, ad est trovi il \u001B[32mlaboratorio\u001B[0m, probabilmente chiuso con password, mentre ad ovest trovi le scale per raggiungere la \u001B[32mmensa\u001B[0m.",
        "floorNumber": 0,
        "locked": false,
        "south": 0,
        "north": null,
        "west": 3,
        "est": 2,
        "items": [
            0
        ],
        "characters": [
            0,
            1,
            2
        ],
        "oxygen": true,
        "passwordRequired": false
    },
    "2": {
        "roomId": 2,
        "roomName": "Laboratorio",
        "roomDescription": "Laboratorio dove si studiano gli alieni catturati e si fanno esperimenti per estrarre da questi il fosforo, ad ovest trovi la \u001B[32msala meeting\u001B[0m.",
        "lookDescription": "Sei nel laboratorio, vedi l'alieno \u001B[31mNebulor\u001B[0m inerme che cerca di proteggersi, tra voi si frappone lo \u001B[34ms47\u001B[0m cercando di proteggerlo, \nsul tavolo trovi delle note strappate, vicino alle stesse vedi un apparecchio che sembra una \u001B[33mmodifica\u001B[0m per la pistola, ad ovest trovi la sala \u001B[32mmeeting\u001B[0m.",
        "floorNumber": 0,
        "locked": true,
        "south": null,
        "north": null,
        "west": 1,
        "est": null,
        "items": [
            1
        ],
        "characters": [
            6,
            2,
            7
        ],
        "oxygen": true,
        "passwordRequired": true
    },
    "3": {
        "roomId": 3,
        "roomName": "Mensa",
        "roomDescription": "Sei nella mensa, vedi seduti ai tavoli due scienziati, \u001B[34ms56\u001B[0m e \u001B[34ms99\u001B[0m, ad ovest trovi le scale ed ad est la \u001B[32msala motori\u001B[0m.",
        "lookDescription": "Sei nella mensa, vedi seduti ai tavoli due scienziati, \u001B[34ms56\u001B[0m e \u001B[34ms99\u001B[0m, ad ovest trovi le scale ed ad est la \u001B[32msala motori\u001B[0m.",
        "floorNumber": -1,
        "locked": false,
        "south": null,
        "north": null,
        "west": 1,
        "est": 4,
        "items": [],
        "characters": [
            3,
            4,
            2
        ],
        "oxygen": true,
        "passwordRequired": false
    },
    "4": {
        "roomId": 4,
        "roomName": "Sala motori",
        "roomDescription": "Sala motori, dove sono situati tutti i vari componenti che permettere alla navicella di muoversi, ad est trovi la \u001B[32mmensa\u001B[0m, mentre a sud vai nello \u001B[32msgabuzzino\u001B[0m.",
        "lookDescription": "Sei nella sala motori, vedi uno scienziato morto per terra, alzando un po' lo sguardo vedi l'alieno \u001B[31mOrionix\u001B[0m che ti ringhia, sembra ferito, su di un tavolo poco lontano da loro vedi una \u001B[33mchiave\u001B[0m, \nad ovest trovi la \u001B[32mmensa\u001B[0m, a sud trovi uno \u001B[32msgabuzzino\u001B[0m.",
        "floorNumber": -1,
        "locked": false,
        "south": 5,
        "north": null,
        "west": 3,
        "est": null,
        "items": [
            2
        ],
        "characters": [
            5,
            2
        ],
        "oxygen": false,
        "passwordRequired": false
    },
    "5": {
        "roomId": 5,
        "roomName": "Sgabuzzino",
        "roomDescription": "Sgabuzzino molto piccolo dove vengono messi i ricambi per i componenti e gli attrezzi per riparare, a nord trovi la \u001B[32msala motori\u001B[0m.",
        "lookDescription": "Sul pavimento vedi un agente morto sbranato, ma noti dei piccoli segni di bruciatura lungo sul collo, come se qualcuno l'avesse stordito con un taser, \nnoti che stringe un \u001B[33mbiletto\u001B[0m di carta tra le mani, a nord trovi la \u001B[32msala motori\u001B[0m",
        "floorNumber": -1,
        "locked": true,
        "south": null,
        "north": 4,
        "west": null,
        "est": null,
        "items": [
            3
        ],
        "characters": [
            2
        ],
        "oxygen": false,
        "passwordRequired": false
    }
}